phidippus/__init__.py
phidippus/cli.py
phidippus/nvdRequests.py
phidippus/vulnerabilityScanner.py
phidippus-1.2.0.dist-info/licenses/LICENSE
phidippus-1.2.0.dist-info/METADATA
phidippus-1.2.0.dist-info/WHEEL
phidippus-1.2.0.dist-info/entry_points.txt
phidippus-1.2.0.dist-info/top_level.txt
phidippus-1.2.0.dist-info/RECORD
